qnabuilder/__init__.py
qnabuilder/_enums.py
qnabuilder/_utils.py
qnabuilder/qna_bot.py
qna_builder-0.1.3.dist-info/METADATA
qna_builder-0.1.3.dist-info/WHEEL
qna_builder-0.1.3.dist-info/top_level.txt
qna_builder-0.1.3.dist-info/RECORD
