Metadata-Version: 2.1
Name: qna-builder
Version: 0.1.3
Summary: Similarity-based conversational dialog engine for Python.
Home-page: https://github.com/msamsami/qna-builder
Author: Mehdi Samsami
Author-email: mehdisamsami@live.com
Keywords: python,qna,qnabuilder,chat,chatbot,conversation,dialog
Classifier: Topic :: Software Development :: Libraries :: Python Modules
Classifier: Topic :: Text Processing :: Linguistic
Classifier: Topic :: Communications :: Chat
Classifier: Programming Language :: Python :: 3.7
Classifier: Programming Language :: Python :: 3.8
Classifier: Programming Language :: Python :: 3.9
Classifier: License :: OSI Approved :: MIT License
Requires-Python: >=3.7
Requires-Dist: scikit-learn (==1.0.2)
Provides-Extra: dev
Requires-Dist: streamlit (==1.21.0) ; extra == 'dev'
Requires-Dist: pytest (==7.3.1) ; extra == 'dev'
Provides-Extra: editor
Requires-Dist: streamlit (==1.21.0) ; extra == 'editor'
